{"transcript":"izsɑʊ̯kums","exists":true,"definitions":["Vārds vai frāze, ko lieto, lai izteiktu spēcīgas emocijas vai piesaistītu uzmanību.","Aicinājums vai pavēle, kas tiek izteikta skaļi.","Paziņojums vai ziņojums, kas tiek nosūtīts, lai aicinātu uz sanāksmi vai pasākumu."],"examples":["Priecīgs izsaukums atskanēja no pūļa.","Viņa atbildēja uz izsaukumu nekavējoties.","Tika izdots izsaukums uz tiesu."],"lemma":"izsaukums","lemmaPos":"noun","synonyms":["sauciens","aicinājums","uzsaukums"],"number":"singular","pluralForm":"izsaukumi","source":"izsaukums"}